{"count":410,"displayed_count":410,"exact_count":821,"points":[{"City":"Oak Park","County":"Cook","ID":"A-3450008","State":"IL","lat":41.87194,"lng":-87.784178},{"City":"Dolton","County":"Cook","ID":"A-3451939","State":"IL","lat":41.612296,"lng":-87.579092},{"City":"Hanover Park","County":"Cook","ID":"A-167902","State":"IL","lat":42.009418,"lng":-88.144691},{"City":"Chicago","County":"Cook","ID":"A-3450593","State":"IL","lat":41.83745,"lng":-87.6304},{"City":"Chicago","County":"Cook","ID":"A-3445799","State":"IL","lat":41.899002,"lng":-87.68692},{"City":"Chicago","County":"Cook","ID":"A-168230","State":"IL","lat":41.778896,"lng":-87.707977},{"City":"Arlington Heights","County":"Cook","ID":"A-3451726","State":"IL","lat":42.04284,"lng":-87.9888},{"City":"Chicago","County":"Cook","ID":"A-3454219","State":"IL","lat":41.87386,"lng":-87.64562},{"City":"Bartlett","County":"Cook","ID":"A-168163","State":"IL","lat":41.994576,"lng":-88.206566},{"City":"Chicago","County":"Cook","ID":"A-3452838","State":"IL","lat":41.93905,"lng":-87.70762},{"City":"Chicago","County":"Cook","ID":"A-3454220","State":"IL","lat":41.694644,"lng":-87.596863},{"City":"Chicago Ridge","County":"Cook","ID":"A-167356","State":"IL","lat":41.709782,"lng":-87.779579},{"City":"Chicago","County":"Cook","ID":"A-3452260","State":"IL","lat":41.69825,"lng":-87.6554},{"City":"Arlington Heights","County":"Cook","ID":"A-3453646","State":"IL","lat":42.10986,"lng":-87.94645},{"City":"Hanover Park","County":"Cook","ID":"A-3449071","State":"IL","lat":42.00539,"lng":-88.14472},{"City":"Chicago","County":"Cook","ID":"A-3453815","State":"IL","lat":41.8153,"lng":-87.63048},{"City":"Chicago","County":"Cook","ID":"A-3452061","State":"IL","lat":41.98153,"lng":-87.78206},{"City":"Chicago","County":"Cook","ID":"A-3446213","State":"IL","lat":41.74693,"lng":-87.62529},{"City":"Bartlett","County":"Cook","ID":"A-168391","State":"IL","lat":41.994572,"lng":-88.207108},{"City":"Chicago","County":"Cook","ID":"A-3450920","State":"IL","lat":41.65813,"lng":-87.58708},{"City":"Hanover Park","County":"Cook","ID":"A-3446493","State":"IL","lat":41.99519,"lng":-88.16591},{"City":"Chicago","County":"Cook","ID":"A-3452740","State":"IL","lat":41.86719,"lng":-87.64409},{"City":"Chicago","County":"Cook","ID":"A-3449555","State":"IL","lat":41.83371,"lng":-87.63091},{"City":"Chicago","County":"Cook","ID":"A-3446282","State":"IL","lat":41.8153,"lng":-87.63048},{"City":"Chicago","County":"Cook","ID":"A-3450455","State":"IL","lat":41.81624,"lng":-87.63011},{"City":"Chicago Heights","County":"Cook","ID":"A-3449563","State":"IL","lat":41.48709,"lng":-87.57735},{"City":"Chicago","County":"Cook","ID":"A-168486","State":"IL","lat":41.685425,"lng":-87.601822},{"City":"Chicago","County":"Cook","ID":"A-3450218","State":"IL","lat":41.87448,"lng":-87.70435},{"City":"Chicago","County":"Cook","ID":"A-3452998","State":"IL","lat":41.92462,"lng":-87.717486},{"City":"Oak Brook","County":"Cook","ID":"A-3450843","State":"IL","lat":41.831037,"lng":-87.91827},{"City":"Chicago","County":"Cook","ID":"A-3447492","State":"IL","lat":41.91299,"lng":-87.66664},{"City":"Hoffman Estates","County":"Cook","ID":"A-3446499","State":"IL","lat":42.06668,"lng":-88.13387},{"City":"Chicago","County":"Cook","ID":"A-3452695","State":"IL","lat":41.98398,"lng":-87.8479},{"City":"Chicago","County":"Cook","ID":"A-3453465","State":"IL","lat":41.7404,"lng":-87.6251},{"City":"Bartlett","County":"Cook","ID":"A-168780","State":"IL","lat":41.988106,"lng":-88.192619},{"City":"Berwyn","County":"Cook","ID":"A-3446607","State":"IL","lat":41.830186,"lng":-87.784152},{"City":"Chicago","County":"Cook","ID":"A-168958","State":"IL","lat":41.903782,"lng":-87.63961},{"City":"Hanover Park","County":"Cook","ID":"A-168277","State":"IL","lat":41.993412,"lng":-88.162704},{"City":"Chicago Ridge","County":"Cook","ID":"A-3450019","State":"IL","lat":41.699422,"lng":-87.786241},{"City":"Chicago","County":"Cook","ID":"A-3448906","State":"IL","lat":41.86926,"lng":-87.64449},{"City":"Hanover Park","County":"Cook","ID":"A-168010","State":"IL","lat":42.007641,"lng":-88.144699},{"City":"Chicago","County":"Cook","ID":"A-168142","State":"IL","lat":41.786919,"lng":-87.630852},{"City":"Chicago","County":"Cook","ID":"A-3446336","State":"IL","lat":41.83745,"lng":-87.6304},{"City":"Roselle","County":"Cook","ID":"A-3451969","State":"IL","lat":41.99226,"lng":-88.05251},{"City":"Forest Park","County":"Cook","ID":"A-3452730","State":"IL","lat":41.87385,"lng":-87.80817},{"City":"Des Plaines","County":"Cook","ID":"A-167798","State":"IL","lat":41.995487,"lng":-87.874496},{"City":"Chicago","County":"Cook","ID":"A-3453809","State":"IL","lat":41.83394,"lng":-87.63117},{"City":"Hillside","County":"Cook","ID":"A-3450065","State":"IL","lat":41.87,"lng":-87.89189},{"City":"Hanover Park","County":"Cook","ID":"A-168278","State":"IL","lat":42.00539,"lng":-88.14473},{"City":"Chicago","County":"Cook","ID":"A-3446631","State":"IL","lat":41.749151,"lng":-87.741311},{"City":"Chicago","County":"Cook","ID":"A-168899","State":"IL","lat":41.847244,"lng":-87.646461},{"City":"Hanover Park","County":"Cook","ID":"A-167503","State":"IL","lat":42.004539,"lng":-88.139854},{"City":"Posen","County":"Cook","ID":"A-3445910","State":"IL","lat":41.62624,"lng":-87.6772},{"City":"Chicago","County":"Cook","ID":"A-3452253","State":"IL","lat":41.963415,"lng":-87.748081},{"City":"Bartlett","County":"Cook","ID":"A-167833","State":"IL","lat":41.99453,"lng":-88.218353},{"City":"Roselle","County":"Cook","ID":"A-168396","State":"IL","lat":41.991917,"lng":-88.046165},{"City":"Chicago","County":"Cook","ID":"A-3451699","State":"IL","lat":41.78346,"lng":-87.6306},{"City":"Elgin","County":"Cook","ID":"A-168390","State":"IL","lat":42.018471,"lng":-88.237045},{"City":"Chicago","County":"Cook","ID":"A-3445692","State":"IL","lat":41.868031,"lng":-87.64482},{"City":"Forest Park","County":"Cook","ID":"A-168911","State":"IL","lat":41.873405,"lng":-87.815384},{"City":"Chicago","County":"Cook","ID":"A-3445817","State":"IL","lat":41.78322,"lng":-87.63155},{"City":"Hanover Park","County":"Cook","ID":"A-167565","State":"IL","lat":41.999073,"lng":-88.133934},{"City":"Chicago","County":"Cook","ID":"A-3449078","State":"IL","lat":42.01931,"lng":-87.700609},{"City":"Oak Park","County":"Cook","ID":"A-3446005","State":"IL","lat":41.873731,"lng":-87.803929},{"City":"Skokie","County":"Cook","ID":"A-3445640","State":"IL","lat":42.06052,"lng":-87.75565},{"City":"Chicago","County":"Cook","ID":"A-3449007","State":"IL","lat":41.863209,"lng":-87.64457},{"City":"Chicago","County":"Cook","ID":"A-3453321","State":"IL","lat":41.92724,"lng":-87.6871},{"City":"Posen","County":"Cook","ID":"A-167741","State":"IL","lat":41.626064,"lng":-87.691399},{"City":"Chicago","County":"Cook","ID":"A-168710","State":"IL","lat":41.736061,"lng":-87.624985},{"City":"Berwyn","County":"Cook","ID":"A-3453920","State":"IL","lat":41.831459,"lng":-87.780522},{"City":"La Grange","County":"Cook","ID":"A-3446859","State":"IL","lat":41.77155,"lng":-87.90672},{"City":"Chicago","County":"Cook","ID":"A-3450004","State":"IL","lat":41.95881,"lng":-87.7393},{"City":"Chicago","County":"Cook","ID":"A-3447096","State":"IL","lat":41.8509,"lng":-87.64492},{"City":"Cicero","County":"Cook","ID":"A-168114","State":"IL","lat":41.850372,"lng":-87.744247},{"City":"Chicago","County":"Cook","ID":"A-3449947","State":"IL","lat":41.87135,"lng":-87.7528},{"City":"Berwyn","County":"Cook","ID":"A-3446595","State":"IL","lat":41.79673,"lng":-87.8075},{"City":"Chicago","County":"Cook","ID":"A-3452668","State":"IL","lat":41.81915,"lng":-87.63056},{"City":"Chicago","County":"Cook","ID":"A-3448339","State":"IL","lat":41.95082,"lng":-87.72509},{"City":"Berwyn","County":"Cook","ID":"A-3451984","State":"IL","lat":41.79673,"lng":-87.8075},{"City":"Chicago","County":"Cook","ID":"A-3451449","State":"IL","lat":41.79001,"lng":-87.63151},{"City":"Chicago","County":"Cook","ID":"A-167469","State":"IL","lat":41.852894,"lng":-87.630959},{"City":"Chicago","County":"Cook","ID":"A-168745","State":"IL","lat":41.982899,"lng":-87.768349},{"City":"Lemont","County":"Cook","ID":"A-3451963","State":"IL","lat":41.699224,"lng":-87.937768},{"City":"Markham","County":"Cook","ID":"A-3451902","State":"IL","lat":41.59757,"lng":-87.71429},{"City":"Willowbrook","County":"Cook","ID":"A-167533","State":"IL","lat":41.780174,"lng":-87.916672},{"City":"Hillside","County":"Cook","ID":"A-3454461","State":"IL","lat":41.86968,"lng":-87.88883},{"City":"Chicago","County":"Cook","ID":"A-168907","State":"IL","lat":41.917896,"lng":-87.670753},{"City":"Chicago","County":"Cook","ID":"A-3453261","State":"IL","lat":41.75817,"lng":-87.62536},{"City":"Hinsdale","County":"Cook","ID":"A-168214","State":"IL","lat":41.818588,"lng":-87.914391},{"City":"Chicago","County":"Cook","ID":"A-168582","State":"IL","lat":41.736191,"lng":-87.625443},{"City":"Chicago","County":"Cook","ID":"A-3451878","State":"IL","lat":41.90837,"lng":-87.66316},{"City":"Hickory Hills","County":"Cook","ID":"A-3450866","State":"IL","lat":41.72135,"lng":-87.80804},{"City":"Chicago","County":"Cook","ID":"A-3455431","State":"IL","lat":41.86745,"lng":-87.62038},{"City":"Lincolnwood","County":"Cook","ID":"A-3451947","State":"IL","lat":42.00639,"lng":-87.74858},{"City":"Berwyn","County":"Cook","ID":"A-3454473","State":"IL","lat":41.82174,"lng":-87.76309},{"City":"Barrington","County":"Cook","ID":"A-3448728","State":"IL","lat":42.09105,"lng":-88.120999},{"City":"Chicago","County":"Cook","ID":"A-168692","State":"IL","lat":41.881817,"lng":-87.645988},{"City":"Winnetka","County":"Cook","ID":"A-3451796","State":"IL","lat":42.101415,"lng":-87.767235},{"City":"Chicago","County":"Cook","ID":"A-167715","State":"IL","lat":41.837391,"lng":-87.670197},{"City":"Chicago","County":"Cook","ID":"A-3448985","State":"IL","lat":41.769256,"lng":-87.612999},{"City":"Chicago","County":"Cook","ID":"A-3449639","State":"IL","lat":41.70557,"lng":-87.59153},{"City":"Chicago","County":"Cook","ID":"A-3448739","State":"IL","lat":41.74746,"lng":-87.62487},{"City":"Chicago Heights","County":"Cook","ID":"A-3451760","State":"IL","lat":41.50651,"lng":-87.53373},{"City":"Hinsdale","County":"Cook","ID":"A-167592","State":"IL","lat":41.783634,"lng":-87.907791},{"City":"Chicago","County":"Cook","ID":"A-3451728","State":"IL","lat":41.96015,"lng":-87.74245},{"City":"Chicago","County":"Cook","ID":"A-3448760","State":"IL","lat":41.92195,"lng":-87.67776},{"City":"Chicago","County":"Cook","ID":"A-168064","State":"IL","lat":41.903488,"lng":-87.661095},{"City":"Chicago","County":"Cook","ID":"A-3451683","State":"IL","lat":41.85757,"lng":-87.64439},{"City":"Des Plaines","County":"Cook","ID":"A-167799","State":"IL","lat":41.995686,"lng":-87.864182},{"City":"Chicago","County":"Cook","ID":"A-3447826","State":"IL","lat":41.742198,"lng":-87.70218},{"City":"Chicago","County":"Cook","ID":"A-3452845","State":"IL","lat":41.80883,"lng":-87.7689},{"City":"Chicago","County":"Cook","ID":"A-3453752","State":"IL","lat":41.98398,"lng":-87.8479},{"City":"Chicago","County":"Cook","ID":"A-3452480","State":"IL","lat":41.8153,"lng":-87.63048},{"City":"Chicago","County":"Cook","ID":"A-168789","State":"IL","lat":41.95414,"lng":-87.681168},{"City":"Des Plaines","County":"Cook","ID":"A-168832","State":"IL","lat":42.006207,"lng":-87.895401},{"City":"Chicago","County":"Cook","ID":"A-3454221","State":"IL","lat":41.85755,"lng":-87.64662},{"City":"Chicago","County":"Cook","ID":"A-3451970","State":"IL","lat":41.8424,"lng":-87.63065},{"City":"Forest Park","County":"Cook","ID":"A-3452469","State":"IL","lat":41.87385,"lng":-87.80817},{"City":"Chicago","County":"Cook","ID":"A-3452999","State":"IL","lat":41.924629,"lng":-87.716534},{"City":"Chicago","County":"Cook","ID":"A-3448781","State":"IL","lat":41.79001,"lng":-87.63151},{"City":"Chicago","County":"Cook","ID":"A-167529","State":"IL","lat":41.875328,"lng":-87.701065},{"City":"Berwyn","County":"Cook","ID":"A-167322","State":"IL","lat":41.799076,"lng":-87.802094},{"City":"Des Plaines","County":"Cook","ID":"A-168846","State":"IL","lat":42.010075,"lng":-87.868378},{"City":"Chicago","County":"Cook","ID":"A-3453420","State":"IL","lat":41.947635,"lng":-87.737857},{"City":"Chicago","County":"Cook","ID":"A-3454212","State":"IL","lat":41.87537,"lng":-87.64933},{"City":"Chicago","County":"Cook","ID":"A-3449066","State":"IL","lat":41.8714,"lng":-87.74908},{"City":"Chicago","County":"Cook","ID":"A-3449274","State":"IL","lat":41.87891,"lng":-87.66673},{"City":"Oak Forest","County":"Cook","ID":"A-3452205","State":"IL","lat":41.60325,"lng":-87.73647},{"City":"Bartlett","County":"Cook","ID":"A-168025","State":"IL","lat":42.008129,"lng":-88.203148},{"City":"Chicago","County":"Cook","ID":"A-3451427","State":"IL","lat":41.92287,"lng":-87.67877},{"City":"Chicago","County":"Cook","ID":"A-3446245","State":"IL","lat":41.93962,"lng":-87.70819},{"City":"Chicago","County":"Cook","ID":"A-167467","State":"IL","lat":41.729019,"lng":-87.624779},{"City":"Hanover Park","County":"Cook","ID":"A-168842","State":"IL","lat":42.009418,"lng":-88.144691},{"City":"Chicago","County":"Cook","ID":"A-3453170","State":"IL","lat":41.84636,"lng":-87.63839},{"City":"Northbrook","County":"Cook","ID":"A-167765","State":"IL","lat":42.150791,"lng":-87.873451},{"City":"Stone Park","County":"Cook","ID":"A-3455240","State":"IL","lat":41.900221,"lng":-87.88372},{"City":"Chicago","County":"Cook","ID":"A-168629","State":"IL","lat":41.717113,"lng":-87.623756},{"City":"Chicago","County":"Cook","ID":"A-3454617","State":"IL","lat":41.837421,"lng":-87.630399},{"City":"Chicago","County":"Cook","ID":"A-3452742","State":"IL","lat":41.8999,"lng":-87.66046},{"City":"Chicago","County":"Cook","ID":"A-167879","State":"IL","lat":41.686256,"lng":-87.601379},{"City":"Chicago","County":"Cook","ID":"A-3445362","State":"IL","lat":41.68807,"lng":-87.60059},{"City":"Des Plaines","County":"Cook","ID":"A-3449677","State":"IL","lat":42.010286,"lng":-87.908885},{"City":"Chicago","County":"Cook","ID":"A-3452315","State":"IL","lat":41.74746,"lng":-87.62487},{"City":"Dolton","County":"Cook","ID":"A-168215","State":"IL","lat":41.613945,"lng":-87.579033},{"City":"Chicago","County":"Cook","ID":"A-3448864","State":"IL","lat":41.799921,"lng":-87.6309},{"City":"Hickory Hills","County":"Cook","ID":"A-168161","State":"IL","lat":41.718891,"lng":-87.806778},{"City":"Chicago","County":"Cook","ID":"A-3452741","State":"IL","lat":41.81278,"lng":-87.75729},{"City":"Chicago","County":"Cook","ID":"A-3451938","State":"IL","lat":41.87347,"lng":-87.734158},{"City":"Chicago","County":"Cook","ID":"A-3453433","State":"IL","lat":41.90401,"lng":-87.62499},{"City":"Chicago","County":"Cook","ID":"A-3452674","State":"IL","lat":41.819,"lng":-87.73767},{"City":"Tinley Park","County":"Cook","ID":"A-167652","State":"IL","lat":41.556419,"lng":-87.764061},{"City":"Chicago","County":"Cook","ID":"A-168685","State":"IL","lat":41.90382,"lng":-87.637436},{"City":"Chicago","County":"Cook","ID":"A-3452038","State":"IL","lat":41.707621,"lng":-87.65297},{"City":"Chicago","County":"Cook","ID":"A-3450109","State":"IL","lat":41.77354,"lng":-87.62673},{"City":"La Grange","County":"Cook","ID":"A-168058","State":"IL","lat":41.76091,"lng":-87.892639},{"City":"Chicago","County":"Cook","ID":"A-3445503","State":"IL","lat":41.95881,"lng":-87.7393},{"City":"Chicago","County":"Cook","ID":"A-168187","State":"IL","lat":41.962776,"lng":-87.746391},{"City":"Dundee","County":"Cook","ID":"A-3452044","State":"IL","lat":42.08135,"lng":-88.22352},{"City":"Tinley Park","County":"Cook","ID":"A-3452282","State":"IL","lat":41.58277,"lng":-87.73366},{"City":"Chicago","County":"Cook","ID":"A-3451250","State":"IL","lat":41.9392,"lng":-87.719647},{"City":"Chicago","County":"Cook","ID":"A-167959","State":"IL","lat":41.831017,"lng":-87.631088},{"City":"La Grange","County":"Cook","ID":"A-3447064","State":"IL","lat":41.784953,"lng":-87.82912},{"City":"La Grange","County":"Cook","ID":"A-167724","State":"IL","lat":41.76165,"lng":-87.867538},{"City":"Chicago","County":"Cook","ID":"A-3452736","State":"IL","lat":41.86718,"lng":-87.64516},{"City":"Country Club Hills","County":"Cook","ID":"A-168847","State":"IL","lat":41.586189,"lng":-87.713844},{"City":"Chicago","County":"Cook","ID":"A-3449686","State":"IL","lat":41.874,"lng":-87.73206},{"City":"Chicago","County":"Cook","ID":"A-3450018","State":"IL","lat":41.700571,"lng":-87.593892},{"City":"Chicago","County":"Cook","ID":"A-3454216","State":"IL","lat":41.87523,"lng":-87.64807},{"City":"Schiller Park","County":"Cook","ID":"A-3446658","State":"IL","lat":41.95352,"lng":-87.85664},{"City":"Chicago","County":"Cook","ID":"A-3448915","State":"IL","lat":41.8677,"lng":-87.64412},{"City":"Chicago","County":"Cook","ID":"A-167407","State":"IL","lat":41.903248,"lng":-87.674843},{"City":"Chicago","County":"Cook","ID":"A-3454215","State":"IL","lat":41.84544,"lng":-87.64906},{"City":"Chicago","County":"Cook","ID":"A-3450419","State":"IL","lat":41.68556,"lng":-87.66197},{"City":"Chicago","County":"Cook","ID":"A-3454747","State":"IL","lat":41.972798,"lng":-87.77825},{"City":"Matteson","County":"Cook","ID":"A-3447056","State":"IL","lat":41.48909,"lng":-87.74464},{"City":"Tinley Park","County":"Cook","ID":"A-168200","State":"IL","lat":41.550949,"lng":-87.789772},{"City":"Chicago","County":"Cook","ID":"A-3449085","State":"IL","lat":41.909484,"lng":-87.80579},{"City":"Justice","County":"Cook","ID":"A-168338","State":"IL","lat":41.74654,"lng":-87.845055},{"City":"Chicago","County":"Cook","ID":"A-167490","State":"IL","lat":41.953667,"lng":-87.727608},{"City":"Oak Park","County":"Cook","ID":"A-3448335","State":"IL","lat":41.87124,"lng":-87.77922},{"City":"Rolling Meadows","County":"Cook","ID":"A-167623","State":"IL","lat":42.086674,"lng":-88.03138},{"City":"Berkeley","County":"Cook","ID":"A-3450607","State":"IL","lat":41.87662,"lng":-87.91864},{"City":"Chicago","County":"Cook","ID":"A-3448989","State":"IL","lat":41.78346,"lng":-87.6306},{"City":"Chicago","County":"Cook","ID":"A-167408","State":"IL","lat":41.735962,"lng":-87.632675},{"City":"Hillside","County":"Cook","ID":"A-3451167","State":"IL","lat":41.84875,"lng":-87.91898},{"City":"Arlington Heights","County":"Cook","ID":"A-168167","State":"IL","lat":42.117699,"lng":-87.972801},{"City":"Riverside","County":"Cook","ID":"A-3452388","State":"IL","lat":41.827446,"lng":-87.82883},{"City":"Chicago","County":"Cook","ID":"A-3445751","State":"IL","lat":41.87583,"lng":-87.68088},{"City":"Chicago","County":"Cook","ID":"A-3452000","State":"IL","lat":41.98226,"lng":-87.80114},{"City":"Chicago","County":"Cook","ID":"A-3447062","State":"IL","lat":41.97777,"lng":-87.74715},{"City":"Chicago","County":"Cook","ID":"A-3449955","State":"IL","lat":41.95756,"lng":-87.73707},{"City":"Chicago","County":"Cook","ID":"A-3445570","State":"IL","lat":41.72711,"lng":-87.62476},{"City":"Chicago","County":"Cook","ID":"A-3455469","State":"IL","lat":41.842271,"lng":-87.63153},{"City":"Hazel Crest","County":"Cook","ID":"A-3445951","State":"IL","lat":41.578056,"lng":-87.658356},{"City":"Orland Park","County":"Cook","ID":"A-3449769","State":"IL","lat":41.63036,"lng":-87.86049},{"City":"Chicago","County":"Cook","ID":"A-3452233","State":"IL","lat":41.92563,"lng":-87.637349},{"City":"Hickory Hills","County":"Cook","ID":"A-3452843","State":"IL","lat":41.72135,"lng":-87.80804},{"City":"Cicero","County":"Cook","ID":"A-3454474","State":"IL","lat":41.822874,"lng":-87.763129},{"City":"Forest Park","County":"Cook","ID":"A-3446021","State":"IL","lat":41.87385,"lng":-87.80817},{"City":"Chicago","County":"Cook","ID":"A-3446262","State":"IL","lat":41.78255,"lng":-87.63128},{"City":"River Forest","County":"Cook","ID":"A-167455","State":"IL","lat":41.883087,"lng":-87.816177},{"City":"Chicago","County":"Cook","ID":"A-168581","State":"IL","lat":41.832413,"lng":-87.694962},{"City":"Chicago","County":"Cook","ID":"A-3451738","State":"IL","lat":41.87592,"lng":-87.64754},{"City":"South Holland","County":"Cook","ID":"A-3452725","State":"IL","lat":41.60413,"lng":-87.58334},{"City":"Chicago","County":"Cook","ID":"A-3451385","State":"IL","lat":41.877234,"lng":-87.74516},{"City":"La Grange","County":"Cook","ID":"A-3448749","State":"IL","lat":41.7635,"lng":-87.9054},{"City":"Justice","County":"Cook","ID":"A-167954","State":"IL","lat":41.746475,"lng":-87.84446},{"City":"Chicago","County":"Cook","ID":"A-3454504","State":"IL","lat":41.811919,"lng":-87.76282},{"City":"Chicago","County":"Cook","ID":"A-3446351","State":"IL","lat":41.68807,"lng":-87.60059},{"City":"Berwyn","County":"Cook","ID":"A-3452341","State":"IL","lat":41.79673,"lng":-87.8075},{"City":"Skokie","County":"Cook","ID":"A-3449405","State":"IL","lat":42.019694,"lng":-87.763458},{"City":"Hanover Park","County":"Cook","ID":"A-168406","State":"IL","lat":41.990746,"lng":-88.157684},{"City":"Schaumburg","County":"Cook","ID":"A-168307","State":"IL","lat":41.997974,"lng":-88.080109},{"City":"Lemont","County":"Cook","ID":"A-168381","State":"IL","lat":41.687798,"lng":-87.930862},{"City":"Alsip","County":"Cook","ID":"A-3450056","State":"IL","lat":41.669627,"lng":-87.759314},{"City":"Chicago","County":"Cook","ID":"A-3449832","State":"IL","lat":41.98234,"lng":-87.7926},{"City":"Chicago","County":"Cook","ID":"A-3450010","State":"IL","lat":41.96076,"lng":-87.74345},{"City":"Chicago","County":"Cook","ID":"A-3450068","State":"IL","lat":41.879229,"lng":-87.64552},{"City":"Elgin","County":"Cook","ID":"A-168806","State":"IL","lat":42.035637,"lng":-88.260399},{"City":"Chicago","County":"Cook","ID":"A-3449535","State":"IL","lat":41.82788,"lng":-87.63017},{"City":"Chicago","County":"Cook","ID":"A-3448660","State":"IL","lat":41.88201,"lng":-87.64598},{"City":"Chicago Heights","County":"Cook","ID":"A-3452174","State":"IL","lat":41.506413,"lng":-87.533917},{"City":"Alsip","County":"Cook","ID":"A-3446992","State":"IL","lat":41.671958,"lng":-87.763687},{"City":"Chicago","County":"Cook","ID":"A-168800","State":"IL","lat":41.885723,"lng":-87.641281},{"City":"Chicago","County":"Cook","ID":"A-3449201","State":"IL","lat":41.83371,"lng":-87.63091},{"City":"Hanover Park","County":"Cook","ID":"A-3449158","State":"IL","lat":42.00539,"lng":-88.14472},{"City":"Chicago","County":"Cook","ID":"A-3449055","State":"IL","lat":41.850779,"lng":-87.644866},{"City":"Worth","County":"Cook","ID":"A-3449377","State":"IL","lat":41.690107,"lng":-87.782773},{"City":"Hanover Park","County":"Cook","ID":"A-168460","State":"IL","lat":42.007641,"lng":-88.144699},{"City":"Schaumburg","County":"Cook","ID":"A-167640","State":"IL","lat":42.063751,"lng":-88.079384},{"City":"Hillside","County":"Cook","ID":"A-3451955","State":"IL","lat":41.87395,"lng":-87.906018},{"City":"Chicago","County":"Cook","ID":"A-3450781","State":"IL","lat":41.87901,"lng":-87.64587},{"City":"Berkeley","County":"Cook","ID":"A-3446995","State":"IL","lat":41.88246,"lng":-87.91957},{"City":"Oak Forest","County":"Cook","ID":"A-3452204","State":"IL","lat":41.60325,"lng":-87.73647},{"City":"Chicago","County":"Cook","ID":"A-3446257","State":"IL","lat":41.7404,"lng":-87.6251},{"City":"Chicago","County":"Cook","ID":"A-3448237","State":"IL","lat":41.860281,"lng":-87.617784},{"City":"Chicago","County":"Cook","ID":"A-3448767","State":"IL","lat":41.87375,"lng":-87.72416},{"City":"Calumet Park","County":"Cook","ID":"A-167622","State":"IL","lat":41.662937,"lng":-87.662582},{"City":"Chicago","County":"Cook","ID":"A-168354","State":"IL","lat":41.940491,"lng":-87.638283},{"City":"Hanover Park","County":"Cook","ID":"A-3454708","State":"IL","lat":42.00539,"lng":-88.14472},{"City":"Chicago","County":"Cook","ID":"A-3449948","State":"IL","lat":41.95881,"lng":-87.7393},{"City":"Alsip","County":"Cook","ID":"A-3452399","State":"IL","lat":41.66201,"lng":-87.724659},{"City":"Chicago","County":"Cook","ID":"A-3446648","State":"IL","lat":41.98234,"lng":-87.7926},{"City":"Chicago","County":"Cook","ID":"A-168174","State":"IL","lat":41.982594,"lng":-87.789963},{"City":"Chicago","County":"Cook","ID":"A-3451725","State":"IL","lat":41.87548,"lng":-87.64197},{"City":"Hazel Crest","County":"Cook","ID":"A-3446560","State":"IL","lat":41.58497,"lng":-87.68106},{"City":"Chicago","County":"Cook","ID":"A-3449692","State":"IL","lat":41.874007,"lng":-87.731257},{"City":"Chicago","County":"Cook","ID":"A-3452258","State":"IL","lat":41.87448,"lng":-87.70435},{"City":"Chicago","County":"Cook","ID":"A-167380","State":"IL","lat":41.783321,"lng":-87.649757},{"City":"Chicago","County":"Cook","ID":"A-3454459","State":"IL","lat":41.8485,"lng":-87.64321},{"City":"Chicago","County":"Cook","ID":"A-168059","State":"IL","lat":41.903488,"lng":-87.661095},{"City":"Chicago","County":"Cook","ID":"A-168188","State":"IL","lat":41.758385,"lng":-87.615128},{"City":"South Holland","County":"Cook","ID":"A-3450922","State":"IL","lat":41.58342,"lng":-87.58276},{"City":"Chicago","County":"Cook","ID":"A-3452236","State":"IL","lat":41.92563,"lng":-87.637625},{"City":"Melrose Park","County":"Cook","ID":"A-168241","State":"IL","lat":41.906425,"lng":-87.919235},{"City":"Hazel Crest","County":"Cook","ID":"A-168296","State":"IL","lat":41.57835,"lng":-87.636452},{"City":"Chicago","County":"Cook","ID":"A-3445491","State":"IL","lat":41.95184,"lng":-87.72775},{"City":"Lincolnwood","County":"Cook","ID":"A-3449740","State":"IL","lat":42.00639,"lng":-87.74858},{"City":"Chicago","County":"Cook","ID":"A-3453431","State":"IL","lat":41.904,"lng":-87.62579},{"City":"Chicago","County":"Cook","ID":"A-168246","State":"IL","lat":41.946129,"lng":-87.718529},{"City":"Chicago","County":"Cook","ID":"A-3451864","State":"IL","lat":41.7404,"lng":-87.6251},{"City":"Bridgeview","County":"Cook","ID":"A-168697","State":"IL","lat":41.76273,"lng":-87.800285},{"City":"Chicago","County":"Cook","ID":"A-167769","State":"IL","lat":41.877224,"lng":-87.716476},{"City":"Hanover Park","County":"Cook","ID":"A-168433","State":"IL","lat":41.990746,"lng":-88.157684},{"City":"Elgin","County":"Cook","ID":"A-168585","State":"IL","lat":42.023933,"lng":-88.237617},{"City":"Chicago","County":"Cook","ID":"A-3448611","State":"IL","lat":41.95917,"lng":-87.74051},{"City":"Chicago","County":"Cook","ID":"A-3452358","State":"IL","lat":41.88051,"lng":-87.64593},{"City":"Berkeley","County":"Cook","ID":"A-3447068","State":"IL","lat":41.882902,"lng":-87.92043},{"City":"Morton Grove","County":"Cook","ID":"A-3449952","State":"IL","lat":42.03869,"lng":-87.76461},{"City":"Schaumburg","County":"Cook","ID":"A-3449593","State":"IL","lat":42.001041,"lng":-88.124251},{"City":"Chicago","County":"Cook","ID":"A-3451740","State":"IL","lat":41.86926,"lng":-87.64449},{"City":"Bartlett","County":"Cook","ID":"A-168647","State":"IL","lat":41.991875,"lng":-88.174126},{"City":"Chicago","County":"Cook","ID":"A-3451739","State":"IL","lat":41.87268,"lng":-87.64462},{"City":"Chicago","County":"Cook","ID":"A-167808","State":"IL","lat":41.848221,"lng":-87.612549},{"City":"Chicago","County":"Cook","ID":"A-3454210","State":"IL","lat":41.87248,"lng":-87.64574},{"City":"Elgin","County":"Cook","ID":"A-168938","State":"IL","lat":42.046616,"lng":-88.238457},{"City":"Chicago","County":"Cook","ID":"A-3446318","State":"IL","lat":41.8355,"lng":-87.68427},{"City":"Chicago","County":"Cook","ID":"A-167495","State":"IL","lat":41.925018,"lng":-87.683182},{"City":"Chicago","County":"Cook","ID":"A-3445975","State":"IL","lat":41.87132,"lng":-87.75471},{"City":"Elgin","County":"Cook","ID":"A-168951","State":"IL","lat":42.031536,"lng":-88.257942},{"City":"Chicago","County":"Cook","ID":"A-3453161","State":"IL","lat":41.8509,"lng":-87.64492},{"City":"Forest Park","County":"Cook","ID":"A-168343","State":"IL","lat":41.87146,"lng":-87.833031},{"City":"Dolton","County":"Cook","ID":"A-3446485","State":"IL","lat":41.615483,"lng":-87.57881},{"City":"Chicago","County":"Cook","ID":"A-3445859","State":"IL","lat":41.89972,"lng":-87.66085},{"City":"Bartlett","County":"Cook","ID":"A-167893","State":"IL","lat":42.008129,"lng":-88.203148},{"City":"Chicago","County":"Cook","ID":"A-168231","State":"IL","lat":41.954678,"lng":-87.6446},{"City":"Hanover Park","County":"Cook","ID":"A-168694","State":"IL","lat":41.990746,"lng":-88.157684},{"City":"Des Plaines","County":"Cook","ID":"A-3454311","State":"IL","lat":42.011535,"lng":-87.91355},{"City":"Chicago","County":"Cook","ID":"A-167788","State":"IL","lat":41.83728,"lng":-87.675339},{"City":"Chicago","County":"Cook","ID":"A-3451335","State":"IL","lat":41.983176,"lng":-87.82352},{"City":"Franklin Park","County":"Cook","ID":"A-3448533","State":"IL","lat":41.93134,"lng":-87.9203},{"City":"Roselle","County":"Cook","ID":"A-168439","State":"IL","lat":41.993389,"lng":-88.060654},{"City":"Rolling Meadows","County":"Cook","ID":"A-168050","State":"IL","lat":42.081993,"lng":-88.030502},{"City":"Chicago","County":"Cook","ID":"A-168538","State":"IL","lat":41.876465,"lng":-87.645416},{"City":"Chicago","County":"Cook","ID":"A-3449304","State":"IL","lat":41.97545,"lng":-87.736857},{"City":"Riverdale","County":"Cook","ID":"A-168410","State":"IL","lat":41.662781,"lng":-87.662827},{"City":"Chicago","County":"Cook","ID":"A-3447954","State":"IL","lat":41.71448,"lng":-87.6468},{"City":"Hanover Park","County":"Cook","ID":"A-167414","State":"IL","lat":42.003994,"lng":-88.136177},{"City":"Calumet City","County":"Cook","ID":"A-3445620","State":"IL","lat":41.63652,"lng":-87.57854},{"City":"Chicago","County":"Cook","ID":"A-3445929","State":"IL","lat":41.735989,"lng":-87.632286},{"City":"Chicago","County":"Cook","ID":"A-3453309","State":"IL","lat":41.7404,"lng":-87.6251},{"City":"Chicago","County":"Cook","ID":"A-3452224","State":"IL","lat":41.88314,"lng":-87.64558},{"City":"Chicago","County":"Cook","ID":"A-3451750","State":"IL","lat":41.73148,"lng":-87.62443},{"City":"Chicago","County":"Cook","ID":"A-3449211","State":"IL","lat":41.87181,"lng":-87.74495},{"City":"Chicago","County":"Cook","ID":"A-168728","State":"IL","lat":41.840748,"lng":-87.713455},{"City":"Arlington Heights","County":"Cook","ID":"A-3449412","State":"IL","lat":42.127768,"lng":-88.002459},{"City":"Hoffman Estates","County":"Cook","ID":"A-3453917","State":"IL","lat":42.06651,"lng":-88.14493},{"City":"Chicago","County":"Cook","ID":"A-3454749","State":"IL","lat":41.97316,"lng":-87.77825},{"City":"Chicago","County":"Cook","ID":"A-3446242","State":"IL","lat":41.87162,"lng":-87.75895},{"City":"Skokie","County":"Cook","ID":"A-3452735","State":"IL","lat":42.06052,"lng":-87.75565},{"City":"La Grange","County":"Cook","ID":"A-3451060","State":"IL","lat":41.760782,"lng":-87.891759},{"City":"Des Plaines","County":"Cook","ID":"A-3452613","State":"IL","lat":41.99504,"lng":-87.86606},{"City":"Northbrook","County":"Cook","ID":"A-3454933","State":"IL","lat":42.14982,"lng":-87.79688},{"City":"Chicago","County":"Cook","ID":"A-3454460","State":"IL","lat":41.84241,"lng":-87.65785},{"City":"Chicago","County":"Cook","ID":"A-3454534","State":"IL","lat":41.87173,"lng":-87.75},{"City":"Chicago","County":"Cook","ID":"A-168199","State":"IL","lat":41.723022,"lng":-87.662743},{"City":"Berkeley","County":"Cook","ID":"A-168290","State":"IL","lat":41.890003,"lng":-87.917778},{"City":"Chicago","County":"Cook","ID":"A-3454419","State":"IL","lat":41.66267,"lng":-87.59124},{"City":"Chicago","County":"Cook","ID":"A-3446339","State":"IL","lat":41.85757,"lng":-87.64439},{"City":"Chicago","County":"Cook","ID":"A-167471","State":"IL","lat":41.823723,"lng":-87.630302},{"City":"Glencoe","County":"Cook","ID":"A-3451795","State":"IL","lat":42.13913,"lng":-87.78935},{"City":"Riverdale","County":"Cook","ID":"A-3450921","State":"IL","lat":41.67315,"lng":-87.66178},{"City":"Alsip","County":"Cook","ID":"A-3447946","State":"IL","lat":41.66514,"lng":-87.74773},{"City":"Chicago","County":"Cook","ID":"A-3453140","State":"IL","lat":41.90377,"lng":-87.63743},{"City":"Chicago","County":"Cook","ID":"A-3454429","State":"IL","lat":41.82788,"lng":-87.63017},{"City":"Chicago","County":"Cook","ID":"A-3454224","State":"IL","lat":41.87535,"lng":-87.650952},{"City":"Forest Park","County":"Cook","ID":"A-3452426","State":"IL","lat":41.87215,"lng":-87.82029},{"City":"Chicago","County":"Cook","ID":"A-3451325","State":"IL","lat":41.90033,"lng":-87.66023},{"City":"Chicago","County":"Cook","ID":"A-3455429","State":"IL","lat":41.86758,"lng":-87.6204},{"City":"Hanover Park","County":"Cook","ID":"A-3452202","State":"IL","lat":42.006557,"lng":-88.14472},{"City":"La Grange","County":"Cook","ID":"A-3448751","State":"IL","lat":41.762,"lng":-87.90349},{"City":"Chicago","County":"Cook","ID":"A-3452599","State":"IL","lat":41.91705,"lng":-87.737525},{"City":"Northbrook","County":"Cook","ID":"A-3448079","State":"IL","lat":42.135229,"lng":-87.887032},{"City":"Chicago","County":"Cook","ID":"A-3449092","State":"IL","lat":41.84938,"lng":-87.64451},{"City":"Bartlett","County":"Cook","ID":"A-3451072","State":"IL","lat":42.00445,"lng":-88.18708},{"City":"Hoffman Estates","County":"Cook","ID":"A-3447901","State":"IL","lat":42.06651,"lng":-88.14493},{"City":"Tinley Park","County":"Cook","ID":"A-168926","State":"IL","lat":41.565426,"lng":-87.744431},{"City":"Chicago","County":"Cook","ID":"A-3452847","State":"IL","lat":41.89739,"lng":-87.65938},{"City":"Hanover Park","County":"Cook","ID":"A-167927","State":"IL","lat":42.00539,"lng":-88.14473},{"City":"Hanover Park","County":"Cook","ID":"A-167442","State":"IL","lat":42.002769,"lng":-88.144737},{"City":"Chicago","County":"Cook","ID":"A-3452498","State":"IL","lat":41.98737,"lng":-87.75136},{"City":"Elgin","County":"Cook","ID":"A-3451972","State":"IL","lat":42.018215,"lng":-88.236278},{"City":"Glencoe","County":"Cook","ID":"A-167787","State":"IL","lat":42.137955,"lng":-87.788406},{"City":"Chicago Heights","County":"Cook","ID":"A-168009","State":"IL","lat":41.50621,"lng":-87.577499},{"City":"Chicago","County":"Cook","ID":"A-3451252","State":"IL","lat":41.93923,"lng":-87.717422},{"City":"Park Ridge","County":"Cook","ID":"A-3453249","State":"IL","lat":42.027408,"lng":-87.855187},{"City":"Chicago","County":"Cook","ID":"A-168625","State":"IL","lat":41.838223,"lng":-87.630562},{"City":"Chicago","County":"Cook","ID":"A-3448279","State":"IL","lat":41.808027,"lng":-87.762703},{"City":"Hanover Park","County":"Cook","ID":"A-168292","State":"IL","lat":41.990746,"lng":-88.157684},{"City":"Chicago","County":"Cook","ID":"A-3448436","State":"IL","lat":41.754,"lng":-87.62518},{"City":"Chicago","County":"Cook","ID":"A-3454214","State":"IL","lat":41.87536,"lng":-87.64987},{"City":"Roselle","County":"Cook","ID":"A-3452540","State":"IL","lat":41.9937,"lng":-88.08022},{"City":"Westchester","County":"Cook","ID":"A-3451360","State":"IL","lat":41.870788,"lng":-87.871354},{"City":"Chicago","County":"Cook","ID":"A-168746","State":"IL","lat":41.660339,"lng":-87.588982},{"City":"Chicago","County":"Cook","ID":"A-168496","State":"IL","lat":41.802418,"lng":-87.789238},{"City":"Harvey","County":"Cook","ID":"A-3453343","State":"IL","lat":41.610337,"lng":-87.682476},{"City":"Chicago","County":"Cook","ID":"A-3451897","State":"IL","lat":41.93904,"lng":-87.6367},{"City":"Des Plaines","County":"Cook","ID":"A-167806","State":"IL","lat":42.010075,"lng":-87.868378},{"City":"Evergreen Park","County":"Cook","ID":"A-167336","State":"IL","lat":41.720947,"lng":-87.682076},{"City":"Des Plaines","County":"Cook","ID":"A-3446527","State":"IL","lat":41.99559,"lng":-87.87433},{"City":"Chicago","County":"Cook","ID":"A-3454462","State":"IL","lat":41.847063,"lng":-87.629992},{"City":"Chicago","County":"Cook","ID":"A-3448803","State":"IL","lat":41.84938,"lng":-87.64451},{"City":"Winnetka","County":"Cook","ID":"A-168409","State":"IL","lat":42.101398,"lng":-87.767769},{"City":"Chicago","County":"Cook","ID":"A-3453424","State":"IL","lat":41.93167,"lng":-87.737326},{"City":"Hazel Crest","County":"Cook","ID":"A-3451428","State":"IL","lat":41.57807,"lng":-87.656055},{"City":"Markham","County":"Cook","ID":"A-167475","State":"IL","lat":41.586288,"lng":-87.687347},{"City":"Chicago","County":"Cook","ID":"A-168838","State":"IL","lat":41.939159,"lng":-87.723892},{"City":"Chicago","County":"Cook","ID":"A-167961","State":"IL","lat":41.872311,"lng":-87.742508},{"City":"Hillside","County":"Cook","ID":"A-168621","State":"IL","lat":41.869675,"lng":-87.917023},{"City":"Chicago","County":"Cook","ID":"A-3452743","State":"IL","lat":41.87132,"lng":-87.75471},{"City":"Chicago","County":"Cook","ID":"A-3448697","State":"IL","lat":41.79063,"lng":-87.630663},{"City":"Hanover Park","County":"Cook","ID":"A-3452423","State":"IL","lat":41.990433,"lng":-88.156977},{"City":"Chicago","County":"Cook","ID":"A-3452001","State":"IL","lat":41.80883,"lng":-87.7689},{"City":"Chicago","County":"Cook","ID":"A-3455435","State":"IL","lat":41.86758,"lng":-87.61888},{"City":"Chicago","County":"Cook","ID":"A-3452439","State":"IL","lat":41.95184,"lng":-87.72775},{"City":"Oak Park","County":"Cook","ID":"A-3446265","State":"IL","lat":41.87124,"lng":-87.77922},{"City":"Hanover Park","County":"Cook","ID":"A-3452200","State":"IL","lat":42.007186,"lng":-88.14471},{"City":"Chicago","County":"Cook","ID":"A-3448788","State":"IL","lat":41.81277,"lng":-87.63072},{"City":"Chicago","County":"Cook","ID":"A-3451908","State":"IL","lat":41.82498,"lng":-87.71865},{"City":"Worth","County":"Cook","ID":"A-168798","State":"IL","lat":41.692825,"lng":-87.784081},{"City":"Chicago","County":"Cook","ID":"A-3455374","State":"IL","lat":41.99068,"lng":-87.680322},{"City":"Des Plaines","County":"Cook","ID":"A-3446634","State":"IL","lat":41.98632,"lng":-87.86878},{"City":"Chicago","County":"Cook","ID":"A-3446337","State":"IL","lat":41.847237,"lng":-87.635173},{"City":"Chicago","County":"Cook","ID":"A-3449060","State":"IL","lat":41.843928,"lng":-87.631099},{"City":"Chicago","County":"Cook","ID":"A-167398","State":"IL","lat":41.9202,"lng":-87.674088},{"City":"Chicago","County":"Cook","ID":"A-3451737","State":"IL","lat":41.86597,"lng":-87.64442},{"City":"Chicago","County":"Cook","ID":"A-3451791","State":"IL","lat":41.87065,"lng":-87.76884},{"City":"Chicago","County":"Cook","ID":"A-167763","State":"IL","lat":41.751728,"lng":-87.566246},{"City":"Chicago","County":"Cook","ID":"A-3451684","State":"IL","lat":41.84938,"lng":-87.64451},{"City":"Palatine","County":"Cook","ID":"A-3449632","State":"IL","lat":42.08501,"lng":-88.07791},{"City":"Bartlett","County":"Cook","ID":"A-167491","State":"IL","lat":42.008129,"lng":-88.203148},{"City":"Skokie","County":"Cook","ID":"A-168790","State":"IL","lat":42.035435,"lng":-87.717056},{"City":"Oak Park","County":"Cook","ID":"A-3448502","State":"IL","lat":41.877064,"lng":-87.79414},{"City":"Chicago","County":"Cook","ID":"A-3455228","State":"IL","lat":41.86597,"lng":-87.64442},{"City":"Des Plaines","County":"Cook","ID":"A-3454880","State":"IL","lat":42.01566,"lng":-87.92979},{"City":"Willow Springs","County":"Cook","ID":"A-3446760","State":"IL","lat":41.746564,"lng":-87.855907},{"City":"Chicago","County":"Cook","ID":"A-3447825","State":"IL","lat":41.749889,"lng":-87.701393},{"City":"Chicago","County":"Cook","ID":"A-3455447","State":"IL","lat":41.87534,"lng":-87.70106},{"City":"Franklin Park","County":"Cook","ID":"A-168515","State":"IL","lat":41.951477,"lng":-87.897072},{"City":"Hillside","County":"Cook","ID":"A-168091","State":"IL","lat":41.869602,"lng":-87.917007},{"City":"Chicago","County":"Cook","ID":"A-3454748","State":"IL","lat":41.91795,"lng":-87.66797},{"City":"Melrose Park","County":"Cook","ID":"A-168415","State":"IL","lat":41.906471,"lng":-87.919655},{"City":"Chicago","County":"Cook","ID":"A-168769","State":"IL","lat":41.804222,"lng":-87.590538},{"City":"Hanover Park","County":"Cook","ID":"A-167375","State":"IL","lat":42.00539,"lng":-88.14473},{"City":"Markham","County":"Cook","ID":"A-167720","State":"IL","lat":41.58625,"lng":-87.694489},{"City":"Chicago","County":"Cook","ID":"A-3454005","State":"IL","lat":41.770761,"lng":-87.70295},{"City":"South Holland","County":"Cook","ID":"A-3452751","State":"IL","lat":41.60413,"lng":-87.58334},{"City":"Alsip","County":"Cook","ID":"A-168716","State":"IL","lat":41.662819,"lng":-87.738777},{"City":"Hanover Park","County":"Cook","ID":"A-3448142","State":"IL","lat":42.008357,"lng":-88.154723},{"City":"Chicago","County":"Cook","ID":"A-3449543","State":"IL","lat":41.82376,"lng":-87.72305}]}