{"count":134,"displayed_count":134,"exact_count":266,"points":[{"City":"Hamilton","County":"Loudoun","ID":"A-228716","State":"VA","lat":39.17767,"lng":-77.661041},{"City":"Purcellville","County":"Loudoun","ID":"A-228724","State":"VA","lat":39.187378,"lng":-77.680046},{"City":"Purcellville","County":"Loudoun","ID":"A-228736","State":"VA","lat":39.186554,"lng":-77.687309},{"City":"Leesburg","County":"Loudoun","ID":"A-228759","State":"VA","lat":39.113358,"lng":-77.561928},{"City":"Chantilly","County":"Loudoun","ID":"A-228770","State":"VA","lat":38.91592,"lng":-77.472588},{"City":"Ashburn","County":"Loudoun","ID":"A-228779","State":"VA","lat":39.04467,"lng":-77.519981},{"City":"Leesburg","County":"Loudoun","ID":"A-228947","State":"VA","lat":39.080189,"lng":-77.499268},{"City":"Sterling","County":"Loudoun","ID":"A-228975","State":"VA","lat":39.007561,"lng":-77.418663},{"City":"Sterling","County":"Loudoun","ID":"A-228978","State":"VA","lat":39.037399,"lng":-77.415199},{"City":"Ashburn","County":"Loudoun","ID":"A-229025","State":"VA","lat":39.01672,"lng":-77.489929},{"City":"Sterling","County":"Loudoun","ID":"A-229026","State":"VA","lat":39.028133,"lng":-77.422974},{"City":"Ashburn","County":"Loudoun","ID":"A-229051","State":"VA","lat":39.065563,"lng":-77.469162},{"City":"Sterling","County":"Loudoun","ID":"A-229052","State":"VA","lat":39.017937,"lng":-77.378128},{"City":"Ashburn","County":"Loudoun","ID":"A-229056","State":"VA","lat":38.995388,"lng":-77.482529},{"City":"Ashburn","County":"Loudoun","ID":"A-229063","State":"VA","lat":38.962803,"lng":-77.535683},{"City":"Ashburn","County":"Loudoun","ID":"A-229067","State":"VA","lat":39.071384,"lng":-77.481621},{"City":"Chantilly","County":"Loudoun","ID":"A-229077","State":"VA","lat":38.903252,"lng":-77.493279},{"City":"Sterling","County":"Loudoun","ID":"A-229082","State":"VA","lat":38.942787,"lng":-77.518806},{"City":"Ashburn","County":"Loudoun","ID":"A-229085","State":"VA","lat":38.992279,"lng":-77.563812},{"City":"Sterling","County":"Loudoun","ID":"A-229096","State":"VA","lat":39.024616,"lng":-77.390404},{"City":"Sterling","County":"Loudoun","ID":"A-229104","State":"VA","lat":39.031437,"lng":-77.378784},{"City":"Purcellville","County":"Loudoun","ID":"A-229147","State":"VA","lat":39.13818,"lng":-77.735283},{"City":"Ashburn","County":"Loudoun","ID":"A-229192","State":"VA","lat":39.029106,"lng":-77.48494},{"City":"Leesburg","County":"Loudoun","ID":"A-229209","State":"VA","lat":39.055859,"lng":-77.576469},{"City":"Ashburn","County":"Loudoun","ID":"A-229210","State":"VA","lat":39.001213,"lng":-77.475716},{"City":"Chantilly","County":"Loudoun","ID":"A-229264","State":"VA","lat":38.929428,"lng":-77.518982},{"City":"Ashburn","County":"Loudoun","ID":"A-229321","State":"VA","lat":38.988926,"lng":-77.503784},{"City":"Sterling","County":"Loudoun","ID":"A-229344","State":"VA","lat":39.045811,"lng":-77.408447},{"City":"Ashburn","County":"Loudoun","ID":"A-229359","State":"VA","lat":39.021725,"lng":-77.480446},{"City":"Sterling","County":"Loudoun","ID":"A-229405","State":"VA","lat":38.990513,"lng":-77.458374},{"City":"Leesburg","County":"Loudoun","ID":"A-229420","State":"VA","lat":39.216297,"lng":-77.534485},{"City":"Ashburn","County":"Loudoun","ID":"A-229457","State":"VA","lat":39.028015,"lng":-77.448318},{"City":"Sterling","County":"Loudoun","ID":"A-229458","State":"VA","lat":38.979115,"lng":-77.429192},{"City":"Ashburn","County":"Loudoun","ID":"A-229466","State":"VA","lat":39.001362,"lng":-77.529106},{"City":"Aldie","County":"Loudoun","ID":"A-229480","State":"VA","lat":38.933861,"lng":-77.550285},{"City":"Sterling","County":"Loudoun","ID":"A-229519","State":"VA","lat":38.982819,"lng":-77.454018},{"City":"Paeonian Springs","County":"Loudoun","ID":"A-229529","State":"VA","lat":39.141029,"lng":-77.612144},{"City":"Aldie","County":"Loudoun","ID":"A-229559","State":"VA","lat":38.939552,"lng":-77.545021},{"City":"Middleburg","County":"Loudoun","ID":"A-229575","State":"VA","lat":38.96825,"lng":-77.735023},{"City":"Sterling","County":"Loudoun","ID":"A-229621","State":"VA","lat":39.020523,"lng":-77.408913},{"City":"Purcellville","County":"Loudoun","ID":"A-229649","State":"VA","lat":39.14241,"lng":-77.691803},{"City":"Chantilly","County":"Loudoun","ID":"A-229650","State":"VA","lat":38.932667,"lng":-77.527382},{"City":"Aldie","County":"Loudoun","ID":"A-229681","State":"VA","lat":38.920952,"lng":-77.555756},{"City":"Round Hill","County":"Loudoun","ID":"A-229684","State":"VA","lat":39.134907,"lng":-77.76609},{"City":"Sterling","County":"Loudoun","ID":"A-229706","State":"VA","lat":38.998299,"lng":-77.397133},{"City":"Ashburn","County":"Loudoun","ID":"A-229826","State":"VA","lat":39.010841,"lng":-77.496338},{"City":"Ashburn","County":"Loudoun","ID":"A-229827","State":"VA","lat":39.050591,"lng":-77.4841},{"City":"Sterling","County":"Loudoun","ID":"A-229849","State":"VA","lat":39.034809,"lng":-77.406174},{"City":"Sterling","County":"Loudoun","ID":"A-229861","State":"VA","lat":39.024708,"lng":-77.401581},{"City":"Leesburg","County":"Loudoun","ID":"A-229870","State":"VA","lat":39.270927,"lng":-77.548309},{"City":"Ashburn","County":"Loudoun","ID":"A-229877","State":"VA","lat":39.063992,"lng":-77.481232},{"City":"Chantilly","County":"Loudoun","ID":"A-229983","State":"VA","lat":38.920658,"lng":-77.496666},{"City":"Chantilly","County":"Loudoun","ID":"A-229991","State":"VA","lat":38.936722,"lng":-77.537842},{"City":"Paeonian Springs","County":"Loudoun","ID":"A-230045","State":"VA","lat":39.148983,"lng":-77.614868},{"City":"Purcellville","County":"Loudoun","ID":"A-230054","State":"VA","lat":39.136536,"lng":-77.704643},{"City":"Lovettsville","County":"Loudoun","ID":"A-230101","State":"VA","lat":39.240303,"lng":-77.70105},{"City":"Sterling","County":"Loudoun","ID":"A-230111","State":"VA","lat":38.979443,"lng":-77.443802},{"City":"Ashburn","County":"Loudoun","ID":"A-230123","State":"VA","lat":39.028538,"lng":-77.463852},{"City":"Sterling","County":"Loudoun","ID":"A-230128","State":"VA","lat":39.044598,"lng":-77.390648},{"City":"Hamilton","County":"Loudoun","ID":"A-230155","State":"VA","lat":39.122173,"lng":-77.6791},{"City":"Chantilly","County":"Loudoun","ID":"A-230156","State":"VA","lat":38.925026,"lng":-77.507858},{"City":"Ashburn","County":"Loudoun","ID":"A-230157","State":"VA","lat":39.041668,"lng":-77.474419},{"City":"Sterling","County":"Loudoun","ID":"A-230158","State":"VA","lat":38.992359,"lng":-77.419968},{"City":"Sterling","County":"Loudoun","ID":"A-230159","State":"VA","lat":38.999428,"lng":-77.415291},{"City":"Sterling","County":"Loudoun","ID":"A-230177","State":"VA","lat":38.964851,"lng":-77.428337},{"City":"Sterling","County":"Loudoun","ID":"A-230194","State":"VA","lat":38.963356,"lng":-77.494675},{"City":"Sterling","County":"Loudoun","ID":"A-230229","State":"VA","lat":38.976749,"lng":-77.409317},{"City":"Leesburg","County":"Loudoun","ID":"A-230239","State":"VA","lat":39.112415,"lng":-77.509895},{"City":"Ashburn","County":"Loudoun","ID":"A-230314","State":"VA","lat":39.011105,"lng":-77.45681},{"City":"Chantilly","County":"Loudoun","ID":"A-230541","State":"VA","lat":38.916676,"lng":-77.513268},{"City":"Ashburn","County":"Loudoun","ID":"A-230550","State":"VA","lat":39.041183,"lng":-77.506279},{"City":"Ashburn","County":"Loudoun","ID":"A-230551","State":"VA","lat":39.036819,"lng":-77.497841},{"City":"Middleburg","County":"Loudoun","ID":"A-230564","State":"VA","lat":39.021137,"lng":-77.693375},{"City":"Leesburg","County":"Loudoun","ID":"A-230593","State":"VA","lat":39.076534,"lng":-77.476845},{"City":"Round Hill","County":"Loudoun","ID":"A-230622","State":"VA","lat":39.123379,"lng":-77.805779},{"City":"Sterling","County":"Loudoun","ID":"A-230712","State":"VA","lat":38.989349,"lng":-77.431366},{"City":"Sterling","County":"Loudoun","ID":"A-230865","State":"VA","lat":39.001724,"lng":-77.403328},{"City":"Bluemont","County":"Loudoun","ID":"A-230892","State":"VA","lat":39.117889,"lng":-77.823006},{"City":"Round Hill","County":"Loudoun","ID":"A-230923","State":"VA","lat":39.141239,"lng":-77.753014},{"City":"Ashburn","County":"Loudoun","ID":"A-231073","State":"VA","lat":38.972992,"lng":-77.54126},{"City":"Purcellville","County":"Loudoun","ID":"A-231148","State":"VA","lat":39.202751,"lng":-77.732948},{"City":"Purcellville","County":"Loudoun","ID":"A-231169","State":"VA","lat":39.319805,"lng":-77.71257},{"City":"Chantilly","County":"Loudoun","ID":"A-231170","State":"VA","lat":38.902496,"lng":-77.522453},{"City":"Sterling","County":"Loudoun","ID":"A-231183","State":"VA","lat":39.008228,"lng":-77.398041},{"City":"Sterling","County":"Loudoun","ID":"A-231194","State":"VA","lat":39.01643,"lng":-77.389404},{"City":"Aldie","County":"Loudoun","ID":"A-231255","State":"VA","lat":38.956261,"lng":-77.538963},{"City":"Sterling","County":"Loudoun","ID":"A-231310","State":"VA","lat":39.036743,"lng":-77.428551},{"City":"Ashburn","County":"Loudoun","ID":"A-231540","State":"VA","lat":39.05851,"lng":-77.454712},{"City":"Leesburg","County":"Loudoun","ID":"A-231564","State":"VA","lat":39.134438,"lng":-77.591507},{"City":"Ashburn","County":"Loudoun","ID":"A-231568","State":"VA","lat":38.970177,"lng":-77.524292},{"City":"Aldie","County":"Loudoun","ID":"A-231689","State":"VA","lat":38.944736,"lng":-77.558563},{"City":"Ashburn","County":"Loudoun","ID":"A-231712","State":"VA","lat":39.068703,"lng":-77.507309},{"City":"Ashburn","County":"Loudoun","ID":"A-231731","State":"VA","lat":39.01754,"lng":-77.468231},{"City":"Ashburn","County":"Loudoun","ID":"A-231758","State":"VA","lat":38.992317,"lng":-77.488647},{"City":"Ashburn","County":"Loudoun","ID":"A-231779","State":"VA","lat":39.007595,"lng":-77.485817},{"City":"Round Hill","County":"Loudoun","ID":"A-231802","State":"VA","lat":39.163834,"lng":-77.799522},{"City":"Waterford","County":"Loudoun","ID":"A-231803","State":"VA","lat":39.185852,"lng":-77.668556},{"City":"Leesburg","County":"Loudoun","ID":"A-231820","State":"VA","lat":39.141582,"lng":-77.546005},{"City":"Leesburg","County":"Loudoun","ID":"A-231886","State":"VA","lat":39.07967,"lng":-77.610825},{"City":"Sterling","County":"Loudoun","ID":"A-231887","State":"VA","lat":39.014866,"lng":-77.371941},{"City":"Ashburn","County":"Loudoun","ID":"A-231932","State":"VA","lat":38.981514,"lng":-77.52774},{"City":"Leesburg","County":"Loudoun","ID":"A-232127","State":"VA","lat":39.078957,"lng":-77.573708},{"City":"Chantilly","County":"Loudoun","ID":"A-232128","State":"VA","lat":38.907181,"lng":-77.539101},{"City":"Hamilton","County":"Loudoun","ID":"A-232146","State":"VA","lat":39.137543,"lng":-77.668503},{"City":"Leesburg","County":"Loudoun","ID":"A-232296","State":"VA","lat":39.089439,"lng":-77.518745},{"City":"Lovettsville","County":"Loudoun","ID":"A-232316","State":"VA","lat":39.245644,"lng":-77.619484},{"City":"Chantilly","County":"Loudoun","ID":"A-232335","State":"VA","lat":38.925739,"lng":-77.543839},{"City":"Sterling","County":"Loudoun","ID":"A-232343","State":"VA","lat":39.022717,"lng":-77.424728},{"City":"Leesburg","County":"Loudoun","ID":"A-232345","State":"VA","lat":39.099476,"lng":-77.56118},{"City":"Leesburg","County":"Loudoun","ID":"A-232386","State":"VA","lat":39.106918,"lng":-77.548744},{"City":"Ashburn","County":"Loudoun","ID":"A-232415","State":"VA","lat":39.044289,"lng":-77.450218},{"City":"Sterling","County":"Loudoun","ID":"A-232418","State":"VA","lat":38.98642,"lng":-77.407761},{"City":"Chantilly","County":"Loudoun","ID":"A-232430","State":"VA","lat":38.923496,"lng":-77.524292},{"City":"Ashburn","County":"Loudoun","ID":"A-232446","State":"VA","lat":39.040356,"lng":-77.486824},{"City":"Aldie","County":"Loudoun","ID":"A-232620","State":"VA","lat":38.964455,"lng":-77.609627},{"City":"Ashburn","County":"Loudoun","ID":"A-232626","State":"VA","lat":39.031761,"lng":-77.535538},{"City":"Aldie","County":"Loudoun","ID":"A-232657","State":"VA","lat":38.930336,"lng":-77.590538},{"City":"Ashburn","County":"Loudoun","ID":"A-233037","State":"VA","lat":39.052307,"lng":-77.451935},{"City":"Purcellville","County":"Loudoun","ID":"A-233061","State":"VA","lat":39.258953,"lng":-77.761116},{"City":"Leesburg","County":"Loudoun","ID":"A-233069","State":"VA","lat":39.067017,"lng":-77.573433},{"City":"Aldie","County":"Loudoun","ID":"A-233320","State":"VA","lat":38.966625,"lng":-77.616646},{"City":"Sterling","County":"Loudoun","ID":"A-233374","State":"VA","lat":39.027882,"lng":-77.431259},{"City":"Sterling","County":"Loudoun","ID":"A-233380","State":"VA","lat":39.045422,"lng":-77.430588},{"City":"Leesburg","County":"Loudoun","ID":"A-233429","State":"VA","lat":39.113602,"lng":-77.542053},{"City":"Chantilly","County":"Loudoun","ID":"A-233543","State":"VA","lat":38.916302,"lng":-77.486084},{"City":"Sterling","County":"Loudoun","ID":"A-233564","State":"VA","lat":38.98526,"lng":-77.472069},{"City":"Purcellville","County":"Loudoun","ID":"A-233569","State":"VA","lat":39.156853,"lng":-77.674614},{"City":"Sterling","County":"Loudoun","ID":"A-233570","State":"VA","lat":38.959064,"lng":-77.49926},{"City":"Sterling","County":"Loudoun","ID":"A-3446989","State":"VA","lat":38.99353,"lng":-77.46618},{"City":"Hamilton","County":"Loudoun","ID":"A-3448721","State":"VA","lat":39.135824,"lng":-77.686209},{"City":"Sterling","County":"Loudoun","ID":"A-3449994","State":"VA","lat":38.95189,"lng":-77.53372},{"City":"Chantilly","County":"Loudoun","ID":"A-3453951","State":"VA","lat":38.893025,"lng":-77.54102},{"City":"Leesburg","County":"Loudoun","ID":"A-3454750","State":"VA","lat":39.000485,"lng":-77.571809},{"City":"Leesburg","County":"Loudoun","ID":"A-3454751","State":"VA","lat":39.01725,"lng":-77.575984}]}